{
  "collectionName": "components_events_event_times",
  "info": {
    "displayName": "SingleRepeatingTime",
    "description": ""
  },
  "options": {},
  "attributes": {
    "DateTime": {
      "required": true,
      "type": "datetime"
    },
    "CoverImageOverride": {
      "type": "media",
      "multiple": false,
      "required": false,
      "allowedTypes": [
        "images"
      ]
    },
    "NameOverride": {
      "type": "string"
    },
    "DescriptionOverride": {
      "type": "text"
    },
    "ContactOverride": {
      "type": "relation",
      "relation": "oneToOne",
      "target": "api::contact.contact"
    },
    "LocationOverride": {
      "type": "relation",
      "relation": "oneToOne",
      "target": "api::contact.contact"
    },
    "StopShowingWhenPast": {
      "type": "boolean",
      "default": true,
      "required": true
    },
    "DescriptionAddendum": {
      "type": "text"
    },
    "AdditionalInfoOverride": {
      "type": "enumeration",
      "enum": [
        "None",
        "IsStreamed"
      ],
      "required": false
    },
    "EndDateTime": {
      "type": "datetime"
    }
  }
}
